gymgrid/__init__.py
gymgrid/envs/__init__.py
gymgrid/envs/cliff_env.py
gymgrid/envs/general_grid.py
gymgrid/envs/samples.py
gymgrid/envs/windy_grid.py
gymgrid2/__init__.py
gymgrid2/envs/__init__.py
gymgrid2/envs/cliff_env.py
gymgrid2/envs/general_grid.py
gymgrid2/envs/samples.py
gymgrid2/envs/windy_grid.py
gymgrid2-1.2.6.dist-info/LICENSE
gymgrid2-1.2.6.dist-info/METADATA
gymgrid2-1.2.6.dist-info/WHEEL
gymgrid2-1.2.6.dist-info/top_level.txt
gymgrid2-1.2.6.dist-info/RECORD
