Metadata-Version: 2.1
Name: gymgrid2
Version: 1.2.6
Summary: UNKNOWN
Home-page: https://github.com/CedricHermansBIT/gymgrid
Author: Ruoqi Zhang
Author-email: ruoqi.zhang.666@gmail.com
Maintainer: Cedric Hermans
Maintainer-email: cedric_hermans@hotmail.com
License: UNKNOWN
Platform: UNKNOWN
Classifier: Programming Language :: Python :: 3
Classifier: License :: OSI Approved :: MIT License
Classifier: Operating System :: OS Independent
Requires-Python: >=3.5
License-File: LICENSE
Requires-Dist: gym
Requires-Dist: numpy
